inputscope/__init__.py
inputscope/__main__.py
inputscope/conf.py
inputscope/db.py
inputscope/listener.py
inputscope/main.py
inputscope/util.py
inputscope/webui.py
inputscope/static/heatmap.min.js
inputscope/static/icon.ico
inputscope/static/keyboard.svg
inputscope/static/site.css
inputscope/static/site.js
inputscope/var/inputscope.ini
inputscope/views/base.tpl
inputscope/views/heatmap.tpl
inputscope/views/index.tpl
inputscope/views/input.tpl
inputscope/views/session.tpl
InputScope-1.11.dist-info/LICENSE.md
InputScope-1.11.dist-info/METADATA
InputScope-1.11.dist-info/WHEEL
InputScope-1.11.dist-info/entry_points.txt
InputScope-1.11.dist-info/top_level.txt
InputScope-1.11.dist-info/RECORD
